g/__init__.py
jts/Coord_Converter.py
jts/GeoDistance.py
jts/GeoTools.py
jts/__init__.py
jts-0.0.3.dist-info/LICENSE.txt
jts-0.0.3.dist-info/METADATA
jts-0.0.3.dist-info/WHEEL
jts-0.0.3.dist-info/top_level.txt
jts-0.0.3.dist-info/RECORD
