Metadata-Version: 2.1
Name: jts
Version: 0.0.3
Summary: npjx
Home-page: https://github.com/pypa/sampleproject
Author: Li Jing
Author-email: HO1qA0E@gmail.com
License: UNKNOWN
Platform: UNKNOWN
Classifier: Programming Language :: Python :: 3
Classifier: License :: OSI Approved :: MIT License
Classifier: Operating System :: OS Independent
Requires-Python: >=3.6
